[
  {
    "id": "1",
    "typeCurrency": "income",
    "title": "mi primer registro",
    "note": "este es mi primer registro en esta aplicacion",
    "typePayment": "cash",
    "quantity": 2500,
    "tag": "casa",
    "date": "10/9/2024",
    "currency": "MXN",
    "images": [
      {
        "id": "1",
        "img": "back-view-man-carrying-tote-bag.jpg",
        "name": "bag"
      },
      {
        "id": "2",
        "img": "beautiful-t-shirt-black-women-s-simple-streetwear-outdoor-shoot.jpg",
        "name": "bag"
      },
      {
        "id": "3",
        "img": "bedroom.jpg",
        "name": "bag"
      },
      {
        "id": "4",
        "img": "bff-printed-red-hoodie.jpg",
        "name": "bag"
      }
    ]
  },
  {
    "title": "mi segundo registro",
    "date": "10/9/2024",
    "id": "2",
    "tag": "casa",
    "note": "este es mi segundo registro en esta aplicacion",
    "currency": "MXN",
    "typeCurrency": "expense",
    "typePayment": "cash",
    "quantity": 3500,
    "images": []
  },
  {
    "title": "mi tercer registro",
    "date": "10/9/2024",
    "id": "3",
    "tag": "casa",
    "note": "Este es mi tercer registro en esta aplicacion",
    "currency": "MXN",
    "typeCurrency": "expense",
    "typePayment": "cash",
    "quantity": 1500,
    "images": []
  },
  {
    "title": "recien implementado",
    "date": "10/9/2024",
    "id": "4",
    "tag": "casa",
    "note": "Este es mi tercer registro en esta aplicacion",
    "currency": "MXN",
    "typeCurrency": "expense",
    "typePayment": "cash",
    "quantity": 2500,
    "images": []
  },
  {
    "title": "mi cuarto registro",
    "date": "10/9/2024",
    "id": "5",
    "tag": "casa",
    "note": "Este es mi cuarto registro en esta aplicacion",
    "currency": "MXN",
    "typeCurrency": "expense",
    "typePayment": "cash",
    "quantity": 4500,
    "images": []
  },
  {
    "title": "mi cuarto registro",
    "date": "10/9/2024",
    "id": "6",
    "tag": "casa",
    "note": "Este es mi cuarto registro en esta aplicacion",
    "currency": "MXN",
    "typeCurrency": "expense",
    "typePayment": "cash",
    "quantity": 4500,
    "images": []
  },
  {
    "title": "mi cuarto registro",
    "date": "10/9/2024",
    "id": "7",
    "tag": "casa",
    "note": "Este es mi cuarto registro en esta aplicacion",
    "currency": "MXN",
    "typeCurrency": "expense",
    "typePayment": "cash",
    "quantity": 4500,
    "images": []
  },
  {
    "title": "mi cuarto registro",
    "date": "10/9/2024",
    "id": "8",
    "tag": "casa",
    "note": "Este es mi cuarto registro en esta aplicacion",
    "currency": "MXN",
    "typeCurrency": "expense",
    "typePayment": "cash",
    "quantity": 4500,
    "images": []
  },
  {
    "title": "mi cuarto registro",
    "date": "10/9/2024",
    "id": "9",
    "tag": "casa",
    "note": "Este es mi cuarto registro en esta aplicacion",
    "currency": "MXN",
    "typeCurrency": "expense",
    "typePayment": "cash",
    "quantity": 4500,
    "images": []
  },
  {
    "title": "mi cuarto registro",
    "date": "10/9/2024",
    "id": "10",
    "tag": "casa",
    "note": "Este es mi cuarto registro en esta aplicacion",
    "currency": "MXN",
    "typeCurrency": "expense",
    "typePayment": "cash",
    "quantity": 4500,
    "images": []
  },
  {
    "title": "mi cuarto registro",
    "date": "10/9/2024",
    "id": "11",
    "tag": "casa",
    "note": "Este es mi cuarto registro en esta aplicacion",
    "currency": "MXN",
    "typeCurrency": "expense",
    "typePayment": "cash",
    "quantity": 4500,
    "images": []
  }
]
